<?xml version="1.0" encoding="utf-8" ?>
<XnaContent>
  <!-- TODO: replace this Asset with your own XML asset data. -->
  <Asset Type="GameData.LevelN">
    <enemySpawnCd>1700</enemySpawnCd>
    <enemyShootCd>1300</enemyShootCd>
    <enemyBulletSpeed>6</enemyBulletSpeed>
    <enemyMovingSpeed>4</enemyMovingSpeed>
    <enemyAttackDeviationFactor>8</enemyAttackDeviationFactor>
    <enemyAttackChanceFactor>50</enemyAttackChanceFactor>
    <deviationRange>100</deviationRange>
    <enemyAttackRange>1100</enemyAttackRange>
    <enemyTurnAroundFactor>250</enemyTurnAroundFactor>
    <enemyHealth>50</enemyHealth>
    <enemyScore>40</enemyScore>
  </Asset>
</XnaContent>
